vllm_ascend/__init__.py
vllm_ascend/_build_info.py
vllm_ascend/_version.py
vllm_ascend/ascend_config.py
vllm_ascend/ascend_forward_context.py
vllm_ascend/cpu_binding.py
vllm_ascend/envs.py
vllm_ascend/libvllm_ascend_kernels.so
vllm_ascend/meta_registration.py
vllm_ascend/platform.py
vllm_ascend/utils.py
vllm_ascend/vllm_ascend_C.cpython-310-x86_64-linux-gnu.so
vllm_ascend/attention/__init__.py
vllm_ascend/attention/attention_mask.py
vllm_ascend/attention/attention_v1.py
vllm_ascend/attention/mla_v1.py
vllm_ascend/attention/sfa_v1.py
vllm_ascend/attention/utils.py
vllm_ascend/compilation/__init__.py
vllm_ascend/compilation/acl_graph.py
vllm_ascend/core/__init__.py
vllm_ascend/core/recompute_schedule_config.py
vllm_ascend/core/recompute_scheduler.py
vllm_ascend/core/schedule_config.py
vllm_ascend/core/scheduler.py
vllm_ascend/device_allocator/__init__.py
vllm_ascend/device_allocator/camem.py
vllm_ascend/distributed/__init__.py
vllm_ascend/distributed/communicator.py
vllm_ascend/distributed/cpu_offload_connector.py
vllm_ascend/distributed/llmdatadist_c_mgr_connector.py
vllm_ascend/distributed/mooncake_connector.py
vllm_ascend/distributed/mooncake_layerwise_connector.py
vllm_ascend/distributed/parallel_state.py
vllm_ascend/distributed/utils.py
vllm_ascend/distributed/cpu_offload_manager/__init__.py
vllm_ascend/distributed/cpu_offload_manager/cpu_kv_cache_manager.py
vllm_ascend/distributed/cpu_offload_manager/metadata.py
vllm_ascend/distributed/device_communicators/__init__.py
vllm_ascend/distributed/device_communicators/pyhccl.py
vllm_ascend/distributed/device_communicators/pyhccl_wrapper.py
vllm_ascend/distributed/mooncake/__init__.py
vllm_ascend/distributed/mooncake/config_data.py
vllm_ascend/distributed/mooncake/kv_transfer.py
vllm_ascend/distributed/mooncake/mooncake_engine.py
vllm_ascend/distributed/mooncake/mooncake_store.py
vllm_ascend/distributed/mooncake/mooncake_store_connector_v1.py
vllm_ascend-0.11.0.dist-info/LICENSE
vllm_ascend-0.11.0.dist-info/METADATA
vllm_ascend-0.11.0.dist-info/WHEEL
vllm_ascend-0.11.0.dist-info/entry_points.txt
vllm_ascend-0.11.0.dist-info/top_level.txt
vllm_ascend-0.11.0.dist-info/RECORD
