Metadata-Version: 2.1
Name: vllm-ascend
Version: 0.11.0
Summary: vLLM Ascend backend plugin
Home-page: https://github.com/vllm-project/vllm-ascend
Author: vLLM-Ascend team
License: Apache 2.0
Project-URL: Homepage, https://github.com/vllm-project/vllm-ascend
Classifier: Programming Language :: Python :: 3.9
Classifier: Programming Language :: Python :: 3.10
Classifier: Programming Language :: Python :: 3.11
Classifier: License :: OSI Approved :: Apache Software License
Classifier: Intended Audience :: Developers
Classifier: Intended Audience :: Information Technology
Classifier: Intended Audience :: Science/Research
Classifier: Topic :: Scientific/Engineering :: Artificial Intelligence
Classifier: Topic :: Scientific/Engineering :: Information Analysis
Requires-Python: >=3.9
License-File: LICENSE
Requires-Dist: cmake>=3.26
Requires-Dist: decorator
Requires-Dist: einops
Requires-Dist: numpy<2.0.0
Requires-Dist: packaging
Requires-Dist: pip
Requires-Dist: pybind11
Requires-Dist: pyyaml
Requires-Dist: scipy
Requires-Dist: setuptools>=64
Requires-Dist: setuptools-scm>=8
Requires-Dist: torch==2.7.1
Requires-Dist: torchvision
Requires-Dist: wheel
Requires-Dist: opencv-python-headless<=4.11.0.86
Requires-Dist: msgpack
Requires-Dist: quart
Requires-Dist: numba
Requires-Dist: torch-npu==2.7.1
Requires-Dist: transformers<=4.57.1
Requires-Dist: fastapi<0.124.0
